relevantpackage/__init__.py
relevantpackage/relevantpackage.py
relevantpackage-0.1.3.dist-info/LICENSE
relevantpackage-0.1.3.dist-info/METADATA
relevantpackage-0.1.3.dist-info/WHEEL
relevantpackage-0.1.3.dist-info/top_level.txt
relevantpackage-0.1.3.dist-info/RECORD
