Metadata-Version: 2.1
Name: relevantpackage
Version: 0.1.3
Summary: Python package for my relevantpackage.
Home-page: https://github.com/erdogant/relevantpackage
Author: Erdogan Taskesen
Author-email: erdogant@gmail.com
License: UNKNOWN
Download-URL: https://github.com/erdogant/relevantpackage/archive/0.1.3.tar.gz
Platform: UNKNOWN
Classifier: Programming Language :: Python :: 3
Classifier: License :: OSI Approved :: MIT License
Classifier: Operating System :: OS Independent
Requires-Python: >=3
License-File: LICENSE
Requires-Dist: matplotlib
Requires-Dist: numpy
Requires-Dist: pandas
Requires-Dist: tqdm
